core/__init__.py
core/datetime/__init__.py
core/datetime/date_formatter.py
core/fastapi/__init__.py
core/fastapi/response.py
core/global_var/__init__.py
core/global_var/constant.py
core/global_var/global_var.py
core/logging/__init__.py
core/logging/log_name.py
core/logging/logging.py
sirius_common_utils-0.1.0.dist-info/METADATA
sirius_common_utils-0.1.0.dist-info/WHEEL
sirius_common_utils-0.1.0.dist-info/top_level.txt
sirius_common_utils-0.1.0.dist-info/RECORD
