Metadata-Version: 2.1
Name: sirius-common-utils
Version: 0.1.0
Summary: sirius-common-utils
Home-page: https://github.com/yourusername/my_package
Author: Joey Yang
Author-email: 156838991@qq.com
Classifier: Programming Language :: Python :: 3
Classifier: License :: OSI Approved :: MIT License
Classifier: Operating System :: OS Independent
Requires-Python: >=3.6
Requires-Dist: requests
Requires-Dist: numpy
